yowasp_boolector/__init__.py
yowasp_boolector/boolector.wasm
yowasp_boolector-3.2.3.6.post25.dev0.dist-info/METADATA
yowasp_boolector-3.2.3.6.post25.dev0.dist-info/WHEEL
yowasp_boolector-3.2.3.6.post25.dev0.dist-info/entry_points.txt
yowasp_boolector-3.2.3.6.post25.dev0.dist-info/top_level.txt
yowasp_boolector-3.2.3.6.post25.dev0.dist-info/RECORD
