Metadata-Version: 2.1
Name: yowasp-boolector
Version: 3.2.3.6.post25.dev0
Summary: boolector Satisfiability Modulo Theories (SMT) solver
Author-email: "William D. Jones" <thor0505@comcast.net>
License: ISC
Project-URL: Homepage, https://yowasp.org/
Project-URL: Source Code, https://github.com/YoWASP/boolector
Project-URL: Bug Tracker, https://github.com/YoWASP/boolector/issues
Classifier: License :: OSI Approved :: ISC License (ISCL)
Requires-Dist: yowasp-runtime ~=1.12
